rc.v
module rc(clock,Resetn,Q);
input clock,Resetn;
output [3:0]Q;
wire [1:0]c1;
count2 s0(clock,Resetn,c1);
dec24 s1(c1,1'b1,Q);
endmodule

module count2(clock,Resetn,y);
input clock,Resetn;
output [1:0]y;
tff s0(1'b1,clock,Resetn,y[0]);
tff s1(y[0],clock,Resetn,y[1]);
endmodule

module dec24(in,En,y);
input [1:0]in;
input En;
output reg [3:0]y;
integer i;
always @ (in)
for(i=0;i<4;i=i+1)
begin
    if(En)
        y[i]=(in==i)?1:0;
    else
        y=4'd0;
end
endmodule

module tff(T,clock,Resetn,Q);
input T,clock,Resetn;
output reg Q;
always @ (posedge clock)
begin
if(!Resetn)
	Q <= 0;
else
	if(T)
		Q <= ~Q;
	else
		Q <= Q;
end
endmodule

Verilog/rc_tb.v
`timescale 1ns/1ns
`include "rc.v"
module rc_tb();
reg clock, Resetn;
wire[3:0] Q;
rc f1(clock,Resetn, Q);

initial
begin
$dumpfile("rc_tb.vcd");
$dumpvars(0, rc_tb);
clock=0;
forever #10 clock = ~clock;
end

initial
begin
Resetn=0; #20;
Resetn=1; #300;
$display("Test complete");
$finish;
end

endmodule

Verilog/rc_tb.vcd
$date
	Sun Nov 20 19:14:44 2022
$end
$version
	Icarus Verilog
$end
$timescale
	1ns
$end
$scope module rc_tb $end
$var wire 4 ! Q [3:0] $end
$var reg 1 " Resetn $end
$var reg 1 # clock $end
$scope module f1 $end
$var wire 1 " Resetn $end
$var wire 1 # clock $end
$var wire 2 $ c1 [1:0] $end
$var wire 4 % Q [3:0] $end
$scope module s0 $end
$var wire 1 " Resetn $end
$var wire 1 # clock $end
$var wire 2 & y [1:0] $end
$scope module s0 $end
$var wire 1 " Resetn $end
$var wire 1 ' T $end
$var wire 1 # clock $end
$var reg 1 ( Q $end
$upscope $end
$scope module s1 $end
$var wire 1 " Resetn $end
$var wire 1 ) T $end
$var wire 1 # clock $end
$var reg 1 * Q $end
$upscope $end
$upscope $end
$scope module s1 $end
$var wire 1 + En $end
$var wire 2 , in [1:0] $end
$var reg 4 - y [3:0] $end
$var integer 32 . i [31:0] $end
$upscope $end
$upscope $end
$upscope $end
$enddefinitions $end
$comment Show the parameter values. $end
$dumpall
$end
#0
$dumpvars
bx .
bx -
bx ,
1+
x*
x)
x(
1'
bx &
bx %
bx $
0#
0"
bx !
$end
#10
0)
b1 !
b1 %
b1 -
b100 .
0(
b0 $
b0 &
b0 ,
0*
1#
#20
0#
1"
#30
1)
b10 !
b10 %
b10 -
b100 .
b1 $
b1 &
b1 ,
1(
1#
#40
0#
#50
0)
b100 !
b100 %
b100 -
b100 .
0(
b10 $
b10 &
b10 ,
1*
1#
#60
0#
#70
1)
b1000 !
b1000 %
b1000 -
b100 .
b11 $
b11 &
b11 ,
1(
1#
#80
0#
#90
0)
b1 !
b1 %
b1 -
b100 .
0(
b0 $
b0 &
b0 ,
0*
1#
#100
0#
#110
1)
b10 !
b10 %
b10 -
b100 .
b1 $
b1 &
b1 ,
1(
1#
#120
0#
#130
0)
b100 !
b100 %
b100 -
b100 .
0(
b10 $
b10 &
b10 ,
1*
1#
#140
0#
#150
1)
b1000 !
b1000 %
b1000 -
b100 .
b11 $
b11 &
b11 ,
1(
1#
#160
0#
#170
0)
b1 !
b1 %
b1 -
b100 .
0(
b0 $
b0 &
b0 ,
0*
1#
#180
0#
#190
1)
b10 !
b10 %
b10 -
b100 .
b1 $
b1 &
b1 ,
1(
1#
#200
0#
#210
0)
b100 !
b100 %
b100 -
b100 .
0(
b10 $
b10 &
b10 ,
1*
1#
#220
0#
#230
1)
b1000 !
b1000 %
b1000 -
b100 .
b11 $
b11 &
b11 ,
1(
1#
#240
0#
#250
0)
b1 !
b1 %
b1 -
b100 .
0(
b0 $
b0 &
b0 ,
0*
1#
#260
0#
#270
1)
b10 !
b10 %
b10 -
b100 .
b1 $
b1 &
b1 ,
1(
1#
#280
0#
#290
0)
b100 !
b100 %
b100 -
b100 .
0(
b10 $
b10 &
b10 ,
1*
1#
#300
0#
#310
1)
b1000 !
b1000 %
b1000 -
b100 .
b11 $
b11 &
b11 ,
1(
1#
